CHANGES.rst
LICENSE
MANIFEST.in
README.rst
setup.py
pytypo/__init__.py
pytypo/_conv_table.py
pytypo/pytypo.py
pytypo.egg-info/PKG-INFO
pytypo.egg-info/SOURCES.txt
pytypo.egg-info/dependency_links.txt
pytypo.egg-info/top_level.txt