Metadata-Version: 1.1
Name: pytypo
Version: 0.3.0
Summary: corrects English spelling mistakes and normalize. (e.g., "cooooooooooooooollllllllllllll" to "cool")
Home-page: https://github.com/ikegami-yukino/pytypo
Author: Yukino Ikegami
Author-email: yknikgm@gmail.com
License: MIT License
Keywords: normalize,lengthened expression,English,typo,spelling
Platform: POSIX
Platform: Windows
Platform: Unix
Platform: MacOS
Classifier: License :: OSI Approved :: MIT License
Classifier: Operating System :: MacOS
Classifier: Operating System :: Microsoft
Classifier: Operating System :: POSIX
Classifier: Programming Language :: Python
Classifier: Programming Language :: Python :: 2.6
Classifier: Programming Language :: Python :: 2.7
Classifier: Programming Language :: Python :: 3.3
Classifier: Programming Language :: Python :: 3.4
Classifier: Programming Language :: Python :: 3.5
Classifier: Development Status :: 3 - Alpha
Classifier: Intended Audience :: Developers
Classifier: Topic :: Software Development
Classifier: Topic :: Text Processing
Classifier: Natural Language :: English
